Workbook

Sheet Inputs & Assumptions
A1: Carbon Credit Investment Model - Inputs & Assumptions
A3: Base Financial Assumptions
A4: WACC | B4: 0.08
A5: Investor Investment Total | B5: 0
A6: Investment Tenor (Years) | B6: 5
A7: Initial Streaming Percentage | B7: 0.48
A8: Target IRR | B8: 0.2
A9: Target Streaming Percentage | B9: 0.48
A11: Monte Carlo Assumptions
A12: Price Growth Base (Mean) | B12: 0.03
A13: Price Growth Std Dev | B13: 0.02
A14: Volume Multiplier Base (Mean) | B14: 1
A15: Volume Std Dev | B15: 0.15
A16: Use GBM Method | B16: No
A17: GBM Drift (μ) | B17: N/A
A18: GBM Volatility (σ) | B18: N/A
A19: Number of Simulations | B19: 5000

Sheet Valuation Schedule
A1: Valuation Schedule - 20 Year Cash Flow
B3: 2025 | C3: 2026 | D3: 2027 | E3: 2028 | F3: 2029 | G3: 2030 | H3: 2031 | I3: 2032 | J3: 2033 | K3: 2034 | L3: 2035 | M3: 2036 | N3: 2037 | O3: 2038 | P3: 2039 | Q3: 2040 | R3: 2041 | S3: 2042 | T3: 2043 | U3: 2044 | V3: Total
A4: Carbon Credits Gross | B4: 0 | C4: 0 | D4: 0 | E4: 0 | F4: 0 | G4: 0 | H4: 0 | I4: 0 | J4: 0 | K4: 0 | L4: 0 | M4: 0 | N4: 0 | O4: 0 | P4: 0 | Q4: 0 | R4: 0 | S4: 0 | T4: 0 | U4: 0 | V4: =SUM(B4:U4) -> 0
A5: Investor Share of Credits | B5: =B4*'Inputs & Assumptions'!$B$6 -> 0 | C5: =C4*'Inputs & Assumptions'!$B$6 -> 0 | D5: =D4*'Inputs & Assumptions'!$B$6 -> 0 | E5: =E4*'Inputs & Assumptions'!$B$6 -> 0 | F5: =F4*'Inputs & Assumptions'!$B$6 -> 0 | G5: =G4*'Inputs & Assumptions'!$B$6 -> 0 | H5: =H4*'Inputs & Assumptions'!$B$6 -> 0 | I5: =I4*'Inputs & Assumptions'!$B$6 -> 0 | ... U5: =U4*'Inputs & Assumptions'!$B$6 -> 0 | V5: =SUM(B5:U5) -> 0
A6: Base Carbon Price | B6: 0 | C6: 0 | D6: 0 | E6: 0 | F6: 0 | G6: 0 | H6: 0 | I6: 0 | J6: 0 | K6: 0 | L6: 0 | M6: 0 | N6: 0 | O6: 0 | P6: 0 | Q6: 0 | R6: 0 | S6: 0 | T6: 0 | U6: 0
A7: Investor Revenue | B7: =B5*B6 -> 0 | C7: =C5*C6 -> 0 | D7: =D5*D6 -> 0 | E7: =E5*E6 -> 0 | F7: =F5*F6 -> 0 | G7: =G5*G6 -> 0 | H7: =H5*H6 -> 0 | I7: =I5*I6 -> 0 | ... U7: =U5*U6 -> 0 | V7: =SUM(B7:U7) -> 0
A8: Project Implementation Costs | B8: 0 | C8: 0 | D8: 0 | E8: 0 | F8: 0 | G8: 0 | H8: 0 | I8: 0 | J8: 0 | K8: 0 | L8: 0 | M8: 0 | N8: 0 | O8: 0 | P8: 0 | Q8: 0 | R8: 0 | S8: 0 | T8: 0 | U8: 0 | V8: =SUM(B8:U8) -> 0
A9: Investor Investment Drawdown | B9: =IF(1<='Inputs & Assumptions'!$B$5,-'Inputs & Assumptions'!$B$4/'Inputs & Assumptions'!$B$5,0) -> 0 | C9: =IF(2<='Inputs & Assumptions'!$B$5,-'Inputs & Assumptions'!$B$4/'Inputs & Assumptions'!$B$5,0) -> 0 | D9: =IF(3<='Inputs & Assumptions'!$B$5,-'Inputs & Assumptions'!$B$4/'Inputs & Assumptions'!$B$5,0) -> 0 | E9: =IF(4<='Inputs & Assumptions'!$B$5,-'Inputs & Assumptions'!$B$4/'Inputs & Assumptions'!$B$5,0) -> 0 | F9: =IF(5<='Inputs & Assumptions'!$B$5,-'Inputs & Assumptions'!$B$4/'Inputs & Assumptions'!$B$5,0) -> 0 | G9: =IF(6<='Inputs & Assumptions'!$B$5,-'Inputs & Assumptions'!$B$4/'Inputs & Assumptions'!$B$5,0) -> 0 | H9: =IF(7<='Inputs & Assumptions'!$B$5,-'Inputs & Assumptions'!$B$4/'Inputs & Assumptions'!$B$5,0) -> 0 | I9: =IF(8<='Inputs & Assumptions'!$B$5,-'Inputs & Assumptions'!$B$4/'Inputs & Assumptions'!$B$5,0) -> 0 | J9: =IF(9<='Inputs & Assumptions'!$B$5,-'Inputs & Assumptions'!$B$4/'Inputs & Assumptions'!$B$5,0) -> 0 | K9: =IF(10<='Inputs & Assumptions'!$B$5,-'Inputs & Assumptions'!$B$4/'Inputs & Assumptions'!$B$5,0) -> 0 | L9: =IF(11<='Inputs & Assumptions'!$B$5,-'Inputs & Assumptions'!$B$4/'Inputs & Assumptions'!$B$5,0) -> 0 | M9: =IF(12<='Inputs & Assumptions'!$B$5,-'Inputs & Assumptions'!$B$4/'Inputs & Assumptions'!$B$5,0) -> 0 | N9: =IF(13<='Inputs & Assumptions'!$B$5,-'Inputs & Assumptions'!$B$4/'Inputs & Assumptions'!$B$5,0) -> 0 | O9: =IF(14<='Inputs & Assumptions'!$B$5,-'Inputs & Assumptions'!$B$4/'Inputs & Assumptions'!$B$5,0) -> 0 | P9: =IF(15<='Inputs & Assumptions'!$B$5,-'Inputs & Assumptions'!$B$4/'Inputs & Assumptions'!$B$5,0) -> 0 | Q9: =IF(16<='Inputs & Assumptions'!$B$5,-'Inputs & Assumptions'!$B$4/'Inputs & Assumptions'!$B$5,0) -> 0 | R9: =IF(17<='Inputs & Assumptions'!$B$5,-'Inputs & Assumptions'!$B$4/'Inputs & Assumptions'!$B$5,0) -> 0 | S9: =IF(18<='Inputs & Assumptions'!$B$5,-'Inputs & Assumptions'!$B$4/'Inputs & Assumptions'!$B$5,0) -> 0 | T9: =IF(19<='Inputs & Assumptions'!$B$5,-'Inputs & Assumptions'!$B$4/'Inputs & Assumptions'!$B$5,0) -> 0 | U9: =IF(20<='Inputs & Assumptions'!$B$5,-'Inputs & Assumptions'!$B$4/'Inputs & Assumptions'!$B$5,0) -> 0 | V9: =SUM(B9:U9) -> 0
A10: Investor Net Cash Flow | B10: =B7+B9 -> 0 | C10: =C7+C9 -> 0 | D10: =D7+D9 -> 0 | E10: =E7+E9 -> 0 | F10: =F7+F9 -> 0 | G10: =G7+G9 -> 0 | H10: =H7+H9 -> 0 | I10: =I7+I9 -> 0 | ... U10: =U7+U9 -> 0 | V10: =SUM(B10:U10) -> 0
A11: Discount Factor | B11: =1/((1+'Inputs & Assumptions'!$B$3)^(1-1)) -> 0 | C11: =1/((1+'Inputs & Assumptions'!$B$3)^(2-1)) -> 0 | D11: =1/((1+'Inputs & Assumptions'!$B$3)^(3-1)) -> 0 | E11: =1/((1+'Inputs & Assumptions'!$B$3)^(4-1)) -> 0 | F11: =1/((1+'Inputs & Assumptions'!$B$3)^(5-1)) -> 0 | G11: =1/((1+'Inputs & Assumptions'!$B$3)^(6-1)) -> 0 | H11: =1/((1+'Inputs & Assumptions'!$B$3)^(7-1)) -> 0 | I11: =1/((1+'Inputs & Assumptions'!$B$3)^(8-1)) -> 0 | J11: =1/((1+'Inputs & Assumptions'!$B$3)^(9-1)) -> 0 | K11: =1/((1+'Inputs & Assumptions'!$B$3)^(10-1)) -> 0 | L11: =1/((1+'Inputs & Assumptions'!$B$3)^(11-1)) -> 0 | M11: =1/((1+'Inputs & Assumptions'!$B$3)^(12-1)) -> 0 | N11: =1/((1+'Inputs & Assumptions'!$B$3)^(13-1)) -> 0 | O11: =1/((1+'Inputs & Assumptions'!$B$3)^(14-1)) -> 0 | P11: =1/((1+'Inputs & Assumptions'!$B$3)^(15-1)) -> 0 | Q11: =1/((1+'Inputs & Assumptions'!$B$3)^(16-1)) -> 0 | R11: =1/((1+'Inputs & Assumptions'!$B$3)^(17-1)) -> 0 | S11: =1/((1+'Inputs & Assumptions'!$B$3)^(18-1)) -> 0 | T11: =1/((1+'Inputs & Assumptions'!$B$3)^(19-1)) -> 0 | U11: =1/((1+'Inputs & Assumptions'!$B$3)^(20-1)) -> 0
A12: Present Value | B12: =B10*B11 -> 0 | C12: =C10*C11 -> 0 | D12: =D10*D11 -> 0 | E12: =E10*E11 -> 0 | F12: =F10*F11 -> 0 | G12: =G10*G11 -> 0 | H12: =H10*H11 -> 0 | I12: =I10*I11 -> 0 | ... U12: =U10*U11 -> 0 | V12: =SUM(B12:U12) -> 0
A13: Cumulative Cash Flow | B13: =B10 -> 0 | C13: =B13+C10 -> 0 | D13: =C13+D10 -> 0 | E13: =D13+E10 -> 0 | F13: =E13+F10 -> 0 | G13: =F13+G10 -> 0 | H13: =G13+H10 -> 0 | I13: =H13+I10 -> 0 | J13: =I13+J10 -> 0 | ... U13: =T13+U10 -> 0
A14: Cumulative PV | B14: =B12 -> 0 | C14: =B14+C12 -> 0 | D14: =C14+D12 -> 0 | E14: =D14+E12 -> 0 | F14: =E14+F12 -> 0 | G14: =F14+G12 -> 0 | H14: =G14+H12 -> 0 | I14: =H14+I12 -> 0 | J14: =I14+J12 -> 0 | ... U14: =T14+U12 -> 0

Sheet Summary & Results
A1: Summary & Results
A3: Key Financial Metrics
A4: Net Present Value (NPV) | B4: =SUM('Valuation Schedule'!B12:U12) -> 0
A5: Internal Rate of Return (IRR) | B5: =IRR('Valuation Schedule'!B10:U10) -> 0 | C5: (Calculated from cash flows)
A6: Payback Period (Years) | B6: =MATCH(0,'Valuation Schedule'!B13:U13,1) -> 0 | C6: (Years to positive cumulative cash flow)
A8: Target Metrics
A9: Target IRR | B9: ='Inputs & Assumptions'!$B$7 -> 0
A10: Target Streaming Percentage | B10: ='Inputs & Assumptions'!$B$8 -> 0
A11: Actual IRR Achieved | B11: 0

Sheet Analysis
A1: Analysis Modules
A2: Use the sheets below to run advanced analysis modules
A3: Input variables in each sheet, then run Python scripts from Terminal

Sheet Deal Valuation
A1: Deal Valuation
A3: Input Variables:
A4: Target IRR | B4: 0.2
A5: Calculation Type | B5: Solve for Purchase Price
A7: Results:
A8: Maximum Purchase Price
A9: Actual IRR Achieved
A10: Status | B10: Ready - Run Python script

Sheet Monte Carlo Results
A1: Monte Carlo Results
A3: Input Variables:
A4: Number of Simulations | B4: 5000
A5: Use GBM Method | B5: No
A6: Status | B6: Ready - Run Python script

Sheet Sensitivity Analysis
A1: Sensitivity Analysis
A3: Input Variables:
A4: Credit Volume Range (Min) | B4: 0.8
A5: Credit Volume Range (Max) | B5: 1.2
A6: Price Multiplier Range (Min) | B6: 0.9
A7: Price Multiplier Range (Max) | B7: 1.1
A8: Status | B8: Ready - Run Python script

Sheet Breakeven Analysis
A1: Breakeven Analysis
A3: Input Variables:
A4: Metric to Calculate | B4: all
A5: Target NPV | B5: 0
A6: Status | B6: Ready - Run Python script
